{"176226183631994880": {"Risk:": 7, "Username:": "Ben Dover", "Name:": "Save me, I'm snarky", "Modifier:": 1.5, "Role:": "Masterminds of Malware", "Heat:": 0, "Backdoor Creation:": 5, "Hacking Skill:": 5, "Bitcoins:": 0, "Reputation:": "__Script Kiddie__", "XP:": 0, "Level:": 1}, "154216072617132032": {"Reputation:": "__Script Kiddie__", "Username:": "SuohCide", "Name:": "Red River", "Modifier:": 1.5, "Role:": "Masterminds of Malware", "Heat:": 0, "Backdoor Creation:": 5, "Hacking Skill:": 5, "Bitcoins:": 0, "Risk:": 7, "XP:": 0, "Level:": 1}, "288767597837680642": {"Risk:": 7, "Username:": "Puppet Master", "Name:": "Puppet", "Modifier:": 1.5, "Role:": "Masterminds of Malware", "Heat:": 0, "XP:": 0, "Hacking Skill:": 5, "Bitcoins:": 0, "Reputation:": "__Script Kiddie__", "Backdoor Creation:": 5, "Level:": 1}, "307431890955010049": {"Reputation:": "__Script Kiddie__", "Username:": "BitCoinPedoBear", "Name:": "Pedo Bear", "Modifier:": 0.75, "Role:": "Bitcoin Breakers", "Heat:": 0, "XP:": 0, "Hacking Skill:": 1, "Level:": 1, "Risk:": 4, "Backdoor Creation:": 0, "Bitcoins:": 50000}, "132500768317112321": {"Risk:": 7, "Username:": "R00t", "Name:": "Hyperclaw79", "Modifier:": 1.5, "Role:": "Masterminds of Malware", "Heat:": 0, "Backdoor Creation:": 5, "Hacking Skill:": 5, "Bitcoins:": 0, "Reputation:": "__Script Kiddie__", "XP:": 0, "Level:": 1}, "155560903331282955": {"Risk:": 2, "Username:": "Pixx", "Name:": "pixx", "Modifier:": 1, "Role:": "Silvertongued Social Engineers", "Heat:": 0, "Backdoor Creation:": 2, "Hacking Skill:": 3, "Bitcoins:": 5000, "Reputation:": "__Script Kiddie__", "XP:": 0, "Level:": 1}, "241472237490798593": {"Risk:": 2, "Username:": "Airking", "Name:": "Roo cancer stage 4", "Modifier:": 1, "Role:": "Silvertongued Social Engineers", "Heat:": 0, "Backdoor Creation:": 2, "Hacking Skill:": 3, "Bitcoins:": 5000, "Reputation:": "__Script Kiddie__", "XP:": 0, "Level:": 1}, "198022726319996929": {"Risk:": 2, "Username:": "Shiori", "Name:": "Shiori", "Modifier:": 1, "Role:": "Silvertongued Social Engineers", "Heat:": 0, "Backdoor Creation:": 2, "Hacking Skill:": 3, "Bitcoins:": 5000, "Reputation:": "__Script Kiddie__", "XP:": 0, "Level:": 1}, "348187532581928971": {"Name:": "Dralia", "Username:": "Dralia", "Role:": "Silvertongued Social Engineers", "Level:": 1, "XP:": 0, "Modifier:": 1, "Hacking Skill:": 3, "Bitcoins:": 5000, "Backdoor Creation:": 2, "Risk:": 2, "Heat:": 0, "Reputation:": "__Script Kiddie__"}, "276404461516357633": {"Risk:": 7, "Username:": "Nevermore", "Name:": "\u027ea\u0475\u04bd\u014b\ud83d\udc9c", "Modifier:": 1.5, "Role:": "Masterminds of Malware", "Heat:": 0, "Backdoor Creation:": 5, "Hacking Skill:": 5, "Bitcoins:": 0, "Reputation:": "__Script Kiddie__", "XP:": 0, "Level:": 1}, "288088164977868801": {"Risk:": 7, "Username:": "LavFufu", "Name:": "LavenderRiven", "Modifier:": 1.5, "Role:": "Masterminds of Malware", "Heat:": 0, "Backdoor Creation:": 5, "Hacking Skill:": 5, "Bitcoins:": 0, "Reputation:": "__Script Kiddie__", "XP:": 0, "Level:": 1}, "245911018637754368": {"Risk:": 7, "Username:": "Bunu", "Name:": "Bunu", "Modifier:": 1.5, "Role:": "Masterminds of Malware", "Heat:": 0, "Backdoor Creation:": 5, "Hacking Skill:": 5, "Bitcoins:": 0, "Reputation:": "__Script Kiddie__", "XP:": 0, "Level:": 1}}